xpt2046_circuitpython/__init__.py
xpt2046_circuitpython/exceptions.py
xpt2046_circuitpython/xpt2046.py
xpt2046_circuitpython-1.0.3.dist-info/LICENSE.md
xpt2046_circuitpython-1.0.3.dist-info/METADATA
xpt2046_circuitpython-1.0.3.dist-info/WHEEL
xpt2046_circuitpython-1.0.3.dist-info/top_level.txt
xpt2046_circuitpython-1.0.3.dist-info/RECORD
