Metadata-Version: 2.1
Name: xpt2046_circuitpython
Version: 1.0.3
Summary: A simple XPT2046 chip reader designed for use with CircuitPython.
Author-email: humeman <camden@humeman.com>
Project-URL: Homepage, https://github.com/humeman/xpt2046-circuitpython
Project-URL: Bug Reports, https://github.com/humeman/xpt2046-circuitpython/issues
Project-URL: Source, https://github.com/humeman/xpt2046-circuitpython
Project-URL: Docs, https://github.com/humeman/xpt2046-circuitpython/blob/main/docs
Project-URL: Teck Tips, https://tecktip.today
Keywords: xpt,xpt2046,circuitpython,spi,pi,tft
Classifier: Development Status :: 4 - Beta
Classifier: Programming Language :: Python :: 3
Classifier: Programming Language :: Python :: 3.7
Classifier: Programming Language :: Python :: 3.8
Classifier: Programming Language :: Python :: 3.9
Classifier: Programming Language :: Python :: 3.10
Classifier: Programming Language :: Python :: 3.11
Classifier: Programming Language :: Python :: 3 :: Only
Requires-Python: >=3.7
License-File: LICENSE.md
